{"id": 122, "name": "Orange Oil", "ingredients_sharing_molecules": [{"name": "Orange", "wiki": "Orange_(fruit)", "id": 194, "category": "Fruit", "common_molecules": [7983, 7765, 8184, 8635, 26049, 998, 15394, 6877, 11230, 7945, 7460, 6826, 6054, 5283345, 61293, 8164, 9855795, 62350, 12020], "slug": "orange"}, {"name": "Coriander", "wiki": "Coriander", "id": 254, "category": "Herb", "common_molecules": [159055, 5283361, 61665, 15394, 111037, 11230, 7460, 61130, 6054, 5283345, 64685, 8184, 26049, 998], "slug": "coriander"}, {"name": "Tea", "wiki": "Tea", "id": 310, "category": "Plant", "common_molecules": [5352543, 8635, 998, 5282108, 15394, 111037, 11230, 7460, 2879, 6054, 5283345, 22873, 12020], "slug": "tea"}, {"name": "Ginger", "wiki": "Ginger", "id": 333, "category": "Spice", "common_molecules": [159055, 26049, 998, 15394, 111037, 11230, 7460, 61130, 637776, 6054, 5283345, 64685, 12020], "slug": "ginger"}, {"name": "Grapefruit", "wiki": "Grapefruit", "id": 238, "category": "Fruit Citrus", "common_molecules": [26049, 61665, 5282108, 15394, 111037, 11230, 6826, 6054, 61293, 9855795, 62350, 998], "slug": "grapefruit"}, {"name": "Cardamom", "wiki": "Cardamom", "id": 327, "category": "Spice", "common_molecules": [159055, 5282108, 15394, 111037, 11230, 7460, 61130, 6054, 64685, 9855795, 5355853, 998], "slug": "cardamom"}, {"name": "Carrot", "wiki": "Carrot", "id": 368, "category": "Vegetable Root", "common_molecules": [159055, 26049, 998, 5282108, 15394, 111037, 11230, 7460, 326, 5283345, 64685, 6054], "slug": "carrot"}, {"name": "Hyssop Oil", "wiki": "Hyssopus_officinalis", "id": 112, "category": "Essential Oil", "common_molecules": [159055, 26049, 998, 15394, 111037, 11230, 7460, 61130, 326, 64685, 6054], "slug": "hyssop-oil"}, {"name": "Strawberry", "wiki": "Strawberry", "id": 234, "category": "Berry", "common_molecules": [7983, 7765, 8635, 998, 15394, 7945, 7460, 6054, 61293, 22873, 12020], "slug": "strawberry"}, {"name": "Laurel", "wiki": "Laurus_nobilis", "id": 305, "category": "Plant", "common_molecules": [159055, 26049, 998, 15394, 111037, 11230, 7460, 61130, 6054, 64685, 12020], "slug": "laurel"}, {"name": "Celery", "wiki": "Celery", "id": 329, "category": "Spice", "common_molecules": [26049, 5282108, 15394, 111037, 11230, 7945, 7460, 61130, 6054, 9855795, 998], "slug": "celery"}, {"name": "Cinnamon", "wiki": "Cinnamon", "id": 330, "category": "Spice", "common_molecules": [159055, 7194, 26049, 998, 15394, 111037, 11230, 7460, 326, 64685, 6054], "slug": "cinnamon"}, {"name": "Nutmeg", "wiki": "Nutmeg", "id": 336, "category": "Spice", "common_molecules": [159055, 26049, 998, 15394, 111037, 11230, 7460, 61130, 326, 64685, 6054], "slug": "nutmeg"}, {"name": "White Wine", "wiki": "White_wine", "id": 45, "category": "Beverage Alcoholic", "common_molecules": [8635, 61665, 5282108, 7945, 2879, 6054, 61293, 8184, 22873, 998], "slug": "white-wine"}, {"name": "Lovage", "wiki": "Lovage", "id": 116, "category": "Essential Oil", "common_molecules": [159055, 26049, 998, 15394, 111037, 11230, 7460, 6054, 64685, 12020], "slug": "lovage"}, {"name": "Mango", "wiki": "Mango", "id": 190, "category": "Fruit", "common_molecules": [5352543, 998, 15394, 7945, 7460, 2879, 6054, 61293, 9855795, 12020], "slug": "mango"}], "slug": "orange-oil", "category": "Essential Oil"}